HW4/ALU.v
`timescale 1ns / 1ps

module ALU
    #(
        // parameter for the data width
        parameter nb = 16
    )
    (
        // n for input
        // c for control
        // acc register & output
        // flags
        input [nb - 1 : 0] n,
        input [2 : 0] c,
        input clk,
        output reg [nb - 1 : 0] acc,
        output reg C,
        output Z,
        output reg V,
        output S
    ); 
    // temp reg
    reg [nb : 0] temp_reg; 
    // assign wire flags
    assign Z = ~(|acc[nb - 1 : 0]);
    assign S = acc[nb - 1];



    // we handeled sub and add overflow as below : 
    // in addition : if we have a + + sign we should get a + sign ans 
    // we have the same thing in - - case
    // but in the - + or + - case the result sign is unknown 
    // so we said that if our ans sign is not equal to non of the input signs so we have OF
    // in subtraction :  
    // we have the same thing but the unknow results are in case + + and - -
    // and the known cases are + - and - + that the result sign should be + and -(in order)
    // so we checked that if sign res is not equal to fisrt one and equal to second one 
    always @(posedge clk) begin
        // test diffrent cases
        case (c)
        3'b000 : begin
            // hold 
            acc = acc;
            V = 0;
            C = 0;
        end
        3'b001 : begin
            // clear
            acc = 0;
            V = 0;
            C = 0;
            
        end
        3'b010 : begin
            // add
            temp_reg = acc + n;
            if ((temp_reg[nb-1] != acc[nb-1]) & (temp_reg[nb-1] != n[nb-1])) 
		V = 1;
	    else
		V = 0;
	    C = temp_reg[nb];
            acc = temp_reg[nb - 1 : 0];
        end
        3'b011 : begin
            // subtract
            temp_reg = acc - n;
	    if ((temp_reg[nb-1] != acc[nb-1]) & (temp_reg[nb-1] == n[nb-1]))
		V = 1;
	    else 
		V = 0;          
            C = !temp_reg[nb];
            acc = temp_reg[nb - 1 : 0];
            
        end
        3'b100 : begin
            // and
            acc = acc & n;
            V = 0;
            C = 0;
        end
        3'b101 : begin
            // neg
            acc = -acc;
            V = 0;
            C = 0;
        end
        3'b110 : begin
            // not
            acc = ~acc;
            V = 0;
            C = 0;
        end
        3'b111 : begin
            // xor
            acc = acc ^ n;
            V = 0;
            C = 0;
        end
        endcase
    end
endmodule


module TB();
    reg clk;
    reg [15:0]in;
    reg [2:0]control;
    wire [15:0]out;
    wire c;
    wire z;
    wire v;
    wire s;

    ALU #(16) ALU01(
        .n(in) ,
        .c(control) ,
        .clk(clk) ,
        .acc(out) ,
        .C(c) ,
        .Z(z) ,
        .V(v) ,
        .S(s)
    );

    always #5 clk = ~clk; 
    initial begin
        $dumpfile("vcd.vcd");
        $dumpvars(0, TB);

        clk = 0;
        in = 0;
        control = 0;
        
        $display("clear acc");
        control <= 3'b001;
        in <= 16'd120;
        #10;
        $display("out is (B - D): %b - %d\nCarry: %d\nZero: %d\nOverflow: %d\nSign : %d",out ,out ,c ,z ,v ,s);
        

        $display("add value 100");
        control <= 3'b010;
        in <= 16'd100;
        #10;
        $display("out is (B - D): %b - %d\nCarry: %d\nZero: %d\nOverflow: %d\nSign : %d",out ,out ,c ,z ,v ,s);
        

        $display("hold a value in acc");
        control <= 3'b000;
        in <= 16'd120;
        #10;
        $display("out is (B - D): %b - %d\nCarry: %d\nZero: %d\nOverflow: %d\nSign : %d",out ,out ,c ,z ,v ,s);


        $display("sub value 50");
        control <= 3'b011;
        in <= 16'd50;
        #10;
        $display("out is (B - D): %b - %d\nCarry: %d\nZero: %d\nOverflow: %d\nSign : %d",out ,out ,c ,z ,v ,s);
        

        $display("and value with 31");
        control <= 3'b100;
        in <= 16'd31;
        #10; 
        $display("out is (B - D): %b - %d\nCarry: %d\nZero: %d\nOverflow: %d\nSign : %d",out ,out ,c ,z ,v ,s);
        

        $display("neg value of acc");
        control <= 3'b101;
        in <= 16'd0;
        #10;
        $display("out is (B - D): %b - %d\nCarry: %d\nZero: %d\nOverflow: %d\nSign : %d",out ,out ,c ,z ,v ,s);
        

        $display("not value of acc");
        control <= 3'b110;
        in <= 16'd0;
        #10;
        $display("out is (B - D): %b - %d\nCarry: %d\nZero: %d\nOverflow: %d\nSign : %d",out ,out ,c ,z ,v ,s);
        

        $display("xor with 15");
        control <= 3'b111;
        in <= 16'd15;
        #10;
        $display("out is (B - D): %b - %d\nCarry: %d\nZero: %d\nOverflow: %d\nSign : %d",out ,out ,c ,z ,v ,s);
      

	$display("now we are going to test OF");
        $display("clear acc");
        control <= 3'b001;
        in <= 16'd120;
        #10;
        $display("out is (B - D): %b - %d\nCarry: %d\nZero: %d\nOverflow: %d\nSign : %d",out ,out ,c ,z ,v ,s);

	$display("add value 1000");
        control <= 3'b010;
        in <= 16'd1000;
        #10;
        $display("out is (B - D): %b - %d\nCarry: %d\nZero: %d\nOverflow: %d\nSign : %d",out ,out ,c ,z ,v ,s); 

	$display("add value max");
        control <= 3'b010;
        in <= 16'b0111_1111_1111_1111;
        #10;
        $display("out is (B - D): %b - %d\nCarry: %d\nZero: %d\nOverflow: %d\nSign : %d",out ,out ,c ,z ,v ,s); 

    end

endmodule

HW4/vcd.vcd
$date
	Mon Jun 05 14:45:59 2023
$end
$version
	ModelSim Version 10.1d
$end
$timescale
	1ps
$end
$scope module TB $end
$var reg 1 ! clk $end
$var reg 16 " in [15:0] $end
$var reg 3 # control [2:0] $end
$var wire 1 $ out [15] $end
$var wire 1 % out [14] $end
$var wire 1 & out [13] $end
$var wire 1 ' out [12] $end
$var wire 1 ( out [11] $end
$var wire 1 ) out [10] $end
$var wire 1 * out [9] $end
$var wire 1 + out [8] $end
$var wire 1 , out [7] $end
$var wire 1 - out [6] $end
$var wire 1 . out [5] $end
$var wire 1 / out [4] $end
$var wire 1 0 out [3] $end
$var wire 1 1 out [2] $end
$var wire 1 2 out [1] $end
$var wire 1 3 out [0] $end
$var wire 1 4 c $end
$var wire 1 5 z $end
$var wire 1 6 v $end
$var wire 1 7 s $end
$scope module ALU01 $end
$var parameter 32 8 nb $end
$var wire 1 9 n [15] $end
$var wire 1 : n [14] $end
$var wire 1 ; n [13] $end
$var wire 1 < n [12] $end
$var wire 1 = n [11] $end
$var wire 1 > n [10] $end
$var wire 1 ? n [9] $end
$var wire 1 @ n [8] $end
$var wire 1 A n [7] $end
$var wire 1 B n [6] $end
$var wire 1 C n [5] $end
$var wire 1 D n [4] $end
$var wire 1 E n [3] $end
$var wire 1 F n [2] $end
$var wire 1 G n [1] $end
$var wire 1 H n [0] $end
$var wire 1 I c [2] $end
$var wire 1 J c [1] $end
$var wire 1 K c [0] $end
$var wire 1 L clk $end
$var reg 16 M acc [15:0] $end
$var reg 1 N C $end
$var wire 1 5 Z $end
$var reg 1 O V $end
$var wire 1 7 S $end
$var reg 17 P temp_reg [16:0] $end
$upscope $end
$upscope $end
$enddefinitions $end
#0
$dumpvars
0!
b1111000 "
b1 #
bx M
xN
xO
bx P
b10000 8
x3
x2
x1
x0
x/
x.
x-
x,
x+
x*
x)
x(
x'
x&
x%
x$
x4
x5
x6
x7
0L
1K
0J
0I
0H
0G
0F
1E
1D
1C
1B
0A
0@
0?
0>
0=
0<
0;
0:
09
$end
#5000
1!
1L
b0 M
0O
0N
07
15
03
02
01
00
0/
0.
0-
0,
0+
0*
0)
0(
0'
0&
0%
0$
06
04
#10000
0!
0L
b10 #
b1100100 "
1F
0E
0D
0K
1J
#15000
1!
1L
b1100100 P
b1100100 M
05
11
1.
1-
#20000
0!
0L
b0 #
b1111000 "
0F
1E
1D
0J
#25000
1!
1L
#30000
0!
0L
b11 #
b110010 "
1G
0E
0B
1K
1J
#35000
1!
1L
b110010 P
1N
b110010 M
14
12
01
1/
0-
#40000
0!
0L
b100 #
b11111 "
1H
1F
1E
0C
0K
0J
1I
#45000
1!
1L
b10010 M
0N
0.
04
#50000
0!
0L
b101 #
b0 "
0H
0G
0F
0E
0D
1K
#55000
1!
1L
b1111111111101110 M
17
11
10
0/
1.
1-
1,
1+
1*
1)
1(
1'
1&
1%
1$
#60000
0!
0L
b110 #
0K
1J
#65000
1!
1L
b10001 M
07
13
02
01
00
1/
0.
0-
0,
0+
0*
0)
0(
0'
0&
0%
0$
#70000
0!
0L
b111 #
b1111 "
1H
1G
1F
1E
1K
#75000
1!
1L
b11110 M
03
12
11
10
#80000
0!
0L
b1 #
b1111000 "
0H
0G
0F
1D
1C
1B
0J
0I
#85000
1!
1L
b0 M
15
02
01
00
0/
#90000
0!
0L
b10 #
b1111101000 "
0D
1A
1@
1?
0K
1J
#95000
1!
1L
b1111101000 P
b1111101000 M
05
10
1.
1-
1,
1+
1*
#100000
0!
0L
b111111111111111 "
1H
1G
1F
1D
1>
1=
1<
1;
1:
#105000
1!
1L
b1000001111100111 P
1O
b1000001111100111 M
16
17
13
12
11
00
1$
#110000
0!
0L
#115000
1!
1L
b10000001111100110 P
0O
1N
b1111100110 M
06
14
07
03
0$
#120000
0!
0L
#125000
1!
1L
b1000001111100101 P
1O
0N
b1000001111100101 M
16
04
17
13
02
1$
#130000
0!
0L
#135000
1!
1L
b10000001111100100 P
0O
1N
b1111100100 M
06
14
07
03
0$
#140000
0!
0L
#145000
1!
1L
b1000001111100011 P
1O
0N
b1000001111100011 M
16
04
17
13
12
01
1$
#150000
0!
0L
#155000
1!
1L
b10000001111100010 P
0O
1N
b1111100010 M
06
14
07
03
0$
#160000
0!
0L
#165000
1!
1L
b1000001111100001 P
1O
0N
b1000001111100001 M
16
04
17
13
02
1$
#170000
0!
0L
#175000
1!
1L
b10000001111100000 P
0O
1N
b1111100000 M
06
14
07
03
0$
#180000
0!
0L
#185000
1!
1L
b1000001111011111 P
1O
0N
b1000001111011111 M
16
04
17
13
12
11
10
1/
0.
1$
#190000
0!
0L
#195000
1!
1L
b10000001111011110 P
0O
1N
b1111011110 M
06
14
07
03
0$
#200000
0!
0L
#205000
1!
1L
b1000001111011101 P
1O
0N
b1000001111011101 M
16
04
17
13
02
1$
#210000
0!
0L
#215000
1!
1L
b10000001111011100 P
0O
1N
b1111011100 M
06
14
07
03
0$
#220000
0!
0L
#225000
1!
1L
b1000001111011011 P
1O
0N
b1000001111011011 M
16
04
17
13
12
01
1$
#230000
0!
0L
#235000
1!
1L
b10000001111011010 P
0O
1N
b1111011010 M
06
14
07
03
0$
#240000
0!
0L
#245000
1!
1L
b1000001111011001 P
1O
0N
b1000001111011001 M
16
04
17
13
02
1$
#250000
0!
0L
#255000
1!
1L
b10000001111011000 P
0O
1N
b1111011000 M
06
14
07
03
0$
#260000
0!
0L
#265000
1!
1L
b1000001111010111 P
1O
0N
b1000001111010111 M
16
04
17
13
12
11
00
1$
#270000
0!
0L
#275000
1!
1L
b10000001111010110 P
0O
1N
b1111010110 M
06
14
07
03
0$
#280000
0!
0L
#285000
1!
1L
b1000001111010101 P
1O
0N
b1000001111010101 M
16
04
17
13
02
1$
#290000
0!
0L
#295000
1!
1L
b10000001111010100 P
0O
1N
b1111010100 M
06
14
07
03
0$
#300000
0!
0L
#305000
1!
1L
b1000001111010011 P
1O
0N
b1000001111010011 M
16
04
17
13
12
01
1$
#310000
0!
0L
#315000
1!
1L
b10000001111010010 P
0O
1N
b1111010010 M
06
14
07
03
0$
#320000
0!
0L
#325000
1!
1L
b1000001111010001 P
1O
0N
b1000001111010001 M
16
04
17
13
02
1$
#330000
0!
0L
#335000
1!
1L
b10000001111010000 P
0O
1N
b1111010000 M
06
14
07
03
0$
#340000
0!
0L
#345000
1!
1L
b1000001111001111 P
1O
0N
b1000001111001111 M
16
04
17
13
12
11
10
0/
1$
#350000
0!
0L
#355000
1!
1L
b10000001111001110 P
0O
1N
b1111001110 M
06
14
07
03
0$
#360000
0!
0L
#365000
1!
1L
b1000001111001101 P
1O
0N
b1000001111001101 M
16
04
17
13
02
1$
#370000
0!
0L
#375000
1!
1L
b10000001111001100 P
0O
1N
b1111001100 M
06
14
07
03
0$
#380000
0!
0L
#385000
1!
1L
b1000001111001011 P
1O
0N
b1000001111001011 M
16
04
17
13
12
01
1$
#390000
0!
0L
#395000
1!
1L
b10000001111001010 P
0O
1N
b1111001010 M
06
14
07
03
0$
#400000
0!
0L
#405000
1!
1L
b1000001111001001 P
1O
0N
b1000001111001001 M
16
04
17
13
02
1$
#410000
0!
0L
#415000
1!
1L
b10000001111001000 P
0O
1N
b1111001000 M
06
14
07
03
0$
#420000
0!
0L
#425000
1!
1L
b1000001111000111 P
1O
0N
b1000001111000111 M
16
04
17
13
12
11
00
1$
#430000
0!
0L
#435000
1!
1L
b10000001111000110 P
0O
1N
b1111000110 M
06
14
07
03
0$
#440000
0!
0L
#445000
1!
1L
b1000001111000101 P
1O
0N
b1000001111000101 M
16
04
17
13
02
1$
#450000
0!
0L
#455000
1!
1L
b10000001111000100 P
0O
1N
b1111000100 M
06
14
07
03
0$
#460000
0!
0L
#465000
1!
1L
b1000001111000011 P
1O
0N
b1000001111000011 M
16
04
17
13
12
01
1$
#470000
0!
0L
#475000
1!
1L
b10000001111000010 P
0O
1N
b1111000010 M
06
14
07
03
0$
#480000
0!
0L
#485000
1!
1L
b1000001111000001 P
1O
0N
b1000001111000001 M
16
04
17
13
02
1$
#490000
0!
0L
#495000
1!
1L
b10000001111000000 P
0O
1N
b1111000000 M
06
14
07
03
0$
#500000
0!
0L
#505000
1!
1L
b1000001110111111 P
1O
0N
b1000001110111111 M
16
04
17
13
12
11
10
1/
1.
0-
1$
#510000
0!
0L
#515000
1!
1L
b10000001110111110 P
0O
1N
b1110111110 M
06
14
07
03
0$
#520000
0!
0L
#525000
1!
1L
b1000001110111101 P
1O
0N
b1000001110111101 M
16
04
17
13
02
1$
#530000
0!
0L
#535000
1!
1L
b10000001110111100 P
0O
1N
b1110111100 M
06
14
07
03
0$
#540000
0!
0L
#545000
1!
1L
b1000001110111011 P
1O
0N
b1000001110111011 M
16
04
17
13
12
01
1$
#550000
0!
0L
#555000
1!
1L
b10000001110111010 P
0O
1N
b1110111010 M
06
14
07
03
0$
#560000
0!
0L
#565000
1!
1L
b1000001110111001 P
1O
0N
b1000001110111001 M
16
04
17
13
02
1$
#570000
0!
0L
#575000
1!
1L
b10000001110111000 P
0O
1N
b1110111000 M
06
14
07
03
0$
#580000
0!
0L
#585000
1!
1L
b1000001110110111 P
1O
0N
b1000001110110111 M
16
04
17
13
12
11
00
1$
#590000
0!
0L
#595000
1!
1L
b10000001110110110 P
0O
1N
b1110110110 M
06
14
07
03
0$
#600000
0!
0L
#605000
1!
1L
b1000001110110101 P
1O
0N
b1000001110110101 M
16
04
17
13
02
1$
#610000
0!
0L
#615000
1!
1L
b10000001110110100 P
0O
1N
b1110110100 M
06
14
07
03
0$
#620000
0!
0L
#625000
1!
1L
b1000001110110011 P
1O
0N
b1000001110110011 M
16
04
17
13
12
01
1$
#630000
0!
0L
#635000
1!
1L
b10000001110110010 P
0O
1N
b1110110010 M
06
14
07
03
0$
#640000
0!
0L
#645000
1!
1L
b1000001110110001 P
1O
0N
b1000001110110001 M
16
04
17
13
02
1$
#650000
0!
0L
#655000
1!
1L
b10000001110110000 P
0O
1N
b1110110000 M
06
14
07
03
0$
#660000
0!
0L
#665000
1!
1L
b1000001110101111 P
1O
0N
b1000001110101111 M
16
04
17
13
12
11
10
0/
1$
#670000
0!
0L
#675000
1!
1L
b10000001110101110 P
0O
1N
b1110101110 M
06
14
07
03
0$
#680000
0!
0L
#685000
1!
1L
b1000001110101101 P
1O
0N
b1000001110101101 M
16
04
17
13
02
1$
#690000
0!
0L
#695000
1!
1L
b10000001110101100 P
0O
1N
b1110101100 M
06
14
07
03
0$
#700000
0!
0L
#705000
1!
1L
b1000001110101011 P
1O
0N
b1000001110101011 M
16
04
17
13
12
01
1$
#710000
0!
0L
#715000
1!
1L
b10000001110101010 P
0O
1N
b1110101010 M
06
14
07
03
0$
#720000
0!
0L
#725000
1!
1L
b1000001110101001 P
1O
0N
b1000001110101001 M
16
04
17
13
02
1$
#730000
0!
0L
#735000
1!
1L
b10000001110101000 P
0O
1N
b1110101000 M
06
14
07
03
0$
#740000
0!
0L
#745000
1!
1L
b1000001110100111 P
1O
0N
b1000001110100111 M
16
04
17
13
12
11
00
1$
#750000
0!
0L
#755000
1!
1L
b10000001110100110 P
0O
1N
b1110100110 M
06
14
07
03
0$
#760000
0!
0L
#765000
1!
1L
b1000001110100101 P
1O
0N
b1000001110100101 M
16
04
17
13
02
1$
#770000
0!
0L
#775000
1!
1L
b10000001110100100 P
0O
1N
b1110100100 M
06
14
07
03
0$
#780000
0!
0L
#785000
1!
1L
b1000001110100011 P
1O
0N
b1000001110100011 M
16
04
17
13
12
01
1$
#790000
0!
0L
#795000
1!
1L
b10000001110100010 P
0O
1N
b1110100010 M
06
14
07
03
0$
#800000
0!
0L
#805000
1!
1L
b1000001110100001 P
1O
0N
b1000001110100001 M
16
04
17
13
02
1$
#810000
0!
0L
#815000
1!
1L
b10000001110100000 P
0O
1N
b1110100000 M
06
14
07
03
0$
#820000
0!
0L
#825000
1!
1L
b1000001110011111 P
1O
0N
b1000001110011111 M
16
04
17
13
12
11
10
1/
0.
1$
#830000
0!
0L
#835000
1!
1L
b10000001110011110 P
0O
1N
b1110011110 M
06
14
07
03
0$
#840000
0!
0L
#845000
1!
1L
b1000001110011101 P
1O
0N
b1000001110011101 M
16
04
17
13
02
1$
#850000
0!
0L
#855000
1!
1L
b10000001110011100 P
0O
1N
b1110011100 M
06
14
07
03
0$
#860000
0!
0L
#865000
1!
1L
b1000001110011011 P
1O
0N
b1000001110011011 M
16
04
17
13
12
01
1$
#870000
0!
0L
#875000
1!
1L
b10000001110011010 P
0O
1N
b1110011010 M
06
14
07
03
0$
#880000
0!
0L
#885000
1!
1L
b1000001110011001 P
1O
0N
b1000001110011001 M
16
04
17
13
02
1$
#890000
0!
0L
#895000
1!
1L
b10000001110011000 P
0O
1N
b1110011000 M
06
14
07
03
0$
#900000
0!
0L
#905000
1!
1L
b1000001110010111 P
1O
0N
b1000001110010111 M
16
04
17
13
12
11
00
1$
#910000
0!
0L
#915000
1!
1L
b10000001110010110 P
0O
1N
b1110010110 M
06
14
07
03
0$
#920000
0!
0L
#925000
1!
1L
b1000001110010101 P
1O
0N
b1000001110010101 M
16
04
17
13
02
1$
#930000
0!
0L
#935000
1!
1L
b10000001110010100 P
0O
1N
b1110010100 M
06
14
07
03
0$
#940000
0!
0L
#945000
1!
1L
b1000001110010011 P
1O
0N
b1000001110010011 M
16
04
17
13
12
01
1$
#950000
0!
0L
#955000
1!
1L
b10000001110010010 P
0O
1N
b1110010010 M
06
14
07
03
0$
#960000
0!
0L
#965000
1!
1L
b1000001110010001 P
1O
0N
b1000001110010001 M
16
04
17
13
02
1$
#970000
0!
0L
#975000
1!
1L
b10000001110010000 P
0O
1N
b1110010000 M
06
14
07
03
0$
#980000
0!
0L
#985000
1!
1L
b1000001110001111 P
1O
0N
b1000001110001111 M
16
04
17
13
12
11
10
0/
1$
#990000
0!
0L
#995000
1!
1L
b10000001110001110 P
0O
1N
b1110001110 M
06
14
07
03
0$
#1000000
0!
0L
#1005000
1!
1L
b1000001110001101 P
1O
0N
b1000001110001101 M
16
04
17
13
02
1$
#1010000
0!
0L
#1015000
1!
1L
b10000001110001100 P
0O
1N
b1110001100 M
06
14
07
03
0$
#1020000
0!
0L
#1025000
1!
1L
b1000001110001011 P
1O
0N
b1000001110001011 M
16
04
17
13
12
01
1$
#1030000
0!
0L
#1035000
1!
1L
b10000001110001010 P
0O
1N
b1110001010 M
06
14
07
03
0$
#1040000
0!
0L
#1045000
1!
1L
b1000001110001001 P
1O
0N
b1000001110001001 M
16
04
17
13
02
1$
#1050000
0!
0L
#1055000
1!
1L
b10000001110001000 P
0O
1N
b1110001000 M
06
14
07
03
0$
#1060000
0!
0L
#1065000
1!
1L
b1000001110000111 P
1O
0N
b1000001110000111 M
16
04
17
13
12
11
00
1$
#1070000
0!
0L
#1075000
1!
1L
b10000001110000110 P
0O
1N
b1110000110 M
06
14
07
03
0$
#1080000
0!
0L
#1085000
1!
1L
b1000001110000101 P
1O
0N
b1000001110000101 M
16
04
17
13
02
1$
#1090000
0!
0L
#1095000
1!
1L
b10000001110000100 P
0O
1N
b1110000100 M
06
14
07
03
0$
#1100000
0!
0L
#1105000
1!
1L
b1000001110000011 P
1O
0N
b1000001110000011 M
16
04
17
13
12
01
1$
#1110000
0!
0L
#1115000
1!
1L
b10000001110000010 P
0O
1N
b1110000010 M
06
14
07
03
0$
#1120000
0!
0L
#1125000
1!
1L
b1000001110000001 P
1O
0N
b1000001110000001 M
16
04
17
13
02
1$
#1130000
0!
0L
#1135000
1!
1L
b10000001110000000 P
0O
1N
b1110000000 M
06
14
07
03
0$
#1140000
0!
0L
#1145000
1!
1L
b1000001101111111 P
1O
0N
b1000001101111111 M
16
04
17
13
12
11
10
1/
1.
1-
0,
1$
#1150000
0!
0L
#1155000
1!
1L
b10000001101111110 P
0O
1N
b1101111110 M
06
14
07
03
0$
#1160000
0!
0L
#1165000
1!
1L
b1000001101111101 P
1O
0N
b1000001101111101 M
16
04
17
13
02
1$
#1170000
0!
0L
#1175000
1!
1L
b10000001101111100 P
0O
1N
b1101111100 M
06
14
07
03
0$
#1180000
0!
0L
#1185000
1!
1L
b1000001101111011 P
1O
0N
b1000001101111011 M
16
04
17
13
12
01
1$
#1190000
0!
0L
#1195000
1!
1L
b10000001101111010 P
0O
1N
b1101111010 M
06
14
07
03
0$
#1200000
0!
0L
#1205000
1!
1L
b1000001101111001 P
1O
0N
b1000001101111001 M
16
04
17
13
02
1$
#1210000
0!
0L
#1215000
1!
1L
b10000001101111000 P
0O
1N
b1101111000 M
06
14
07
03
0$
#1220000
0!
0L
#1225000
1!
1L
b1000001101110111 P
1O
0N
b1000001101110111 M
16
04
17
13
12
11
00
1$
#1230000
0!
0L
#1235000
1!
1L
b10000001101110110 P
0O
1N
b1101110110 M
06
14
07
03
0$
#1240000
0!
0L
#1245000
1!
1L
b1000001101110101 P
1O
0N
b1000001101110101 M
16
04
17
13
02
1$
#1250000
0!
0L
#1255000
1!
1L
b10000001101110100 P
0O
1N
b1101110100 M
06
14
07
03
0$
#1260000
0!
0L
#1265000
1!
1L
b1000001101110011 P
1O
0N
b1000001101110011 M
16
04
17
13
12
01
1$
#1270000
0!
0L
#1275000
1!
1L
b10000001101110010 P
0O
1N
b1101110010 M
06
14
07
03
0$
#1280000
0!
0L
#1285000
1!
1L
b1000001101110001 P
1O
0N
b1000001101110001 M
16
04
17
13
02
1$
#1290000
0!
0L
#1295000
1!
1L
b10000001101110000 P
0O
1N
b1101110000 M
06
14
07
03
0$
#1300000
0!
0L
#1305000
1!
1L
b1000001101101111 P
1O
0N
b1000001101101111 M
16
04
17
13
12
11
10
0/
1$
#1310000
0!
0L
#1315000
1!
1L
b10000001101101110 P
0O
1N
b1101101110 M
06
14
07
03
0$
#1320000
0!
0L
#1325000
1!
1L
b1000001101101101 P
1O
0N
b1000001101101101 M
16
04
17
13
02
1$
#1330000
0!
0L
#1335000
1!
1L
b10000001101101100 P
0O
1N
b1101101100 M
06
14
07
03
0$
#1340000
0!
0L
#1345000
1!
1L
b1000001101101011 P
1O
0N
b1000001101101011 M
16
04
17
13
12
01
1$
#1350000
0!
0L
#1355000
1!
1L
b10000001101101010 P
0O
1N
b1101101010 M
06
14
07
03
0$
#1360000
0!
0L
#1365000
1!
1L
b1000001101101001 P
1O
0N
b1000001101101001 M
16
04
17
13
02
1$
#1370000
0!
0L
#1375000
1!
1L
b10000001101101000 P
0O
1N
b1101101000 M
06
14
07
03
0$
#1380000
0!
0L
#1385000
1!
1L
b1000001101100111 P
1O
0N
b1000001101100111 M
16
04
17
13
12
11
00
1$
#1390000
0!
0L
#1395000
1!
1L
b10000001101100110 P
0O
1N
b1101100110 M
06
14
07
03
0$
#1400000
0!
0L
#1405000
1!
1L
b1000001101100101 P
1O
0N
b1000001101100101 M
16
04
17
13
02
1$
#1410000
0!
0L
#1415000
1!
1L
b10000001101100100 P
0O
1N
b1101100100 M
06
14
07
03
0$
#1420000
0!
0L
#1425000
1!
1L
b1000001101100011 P
1O
0N
b1000001101100011 M
16
04
17
13
12
01
1$
#1430000
0!
0L
#1435000
1!
1L
b10000001101100010 P
0O
1N
b1101100010 M
06
14
07
03
0$
#1440000
0!
0L
#1445000
1!
1L
b1000001101100001 P
1O
0N
b1000001101100001 M
16
04
17
13
02
1$
#1450000
0!
0L
#1455000
1!
1L
b10000001101100000 P
0O
1N
b1101100000 M
06
14
07
03
0$
#1460000
0!
0L
#1465000
1!
1L
b1000001101011111 P
1O
0N
b1000001101011111 M
16
04
17
13
12
11
10
1/
0.
1$
#1470000
0!
0L
#1475000
1!
1L
b10000001101011110 P
0O
1N
b1101011110 M
06
14
07
03
0$
#1480000
0!
0L
#1485000
1!
1L
b1000001101011101 P
1O
0N
b1000001101011101 M
16
04
17
13
02
1$
#1490000
0!
0L
#1495000
1!
1L
b10000001101011100 P
0O
1N
b1101011100 M
06
14
07
03
0$
#1500000
0!
0L
#1505000
1!
1L
b1000001101011011 P
1O
0N
b1000001101011011 M
16
04
17
13
12
01
1$
#1510000
0!
0L
#1515000
1!
1L
b10000001101011010 P
0O
1N
b1101011010 M
06
14
07
03
0$
#1520000
0!
0L
#1525000
1!
1L
b1000001101011001 P
1O
0N
b1000001101011001 M
16
04
17
13
02
1$
#1530000
0!
0L
#1535000
1!
1L
b10000001101011000 P
0O
1N
b1101011000 M
06
14
07
03
0$
#1540000
0!
0L
#1545000
1!
1L
b1000001101010111 P
1O
0N
b1000001101010111 M
16
04
17
13
12
11
00
1$
#1550000
0!
0L
#1555000
1!
1L
b10000001101010110 P
0O
1N
b1101010110 M
06
14
07
03
0$
#1560000
0!
0L
#1565000
1!
1L
b1000001101010101 P
1O
0N
b1000001101010101 M
16
04
17
13
02
1$
#1570000
0!
0L
#1575000
1!
1L
b10000001101010100 P
0O
1N
b1101010100 M
06
14
07
03
0$
#1580000
0!
0L
#1585000
1!
1L
b1000001101010011 P
1O
0N
b1000001101010011 M
16
04
17
13
12
01
1$
#1590000
0!
0L
#1595000
1!
1L
b10000001101010010 P
0O
1N
b1101010010 M
06
14
07
03
0$
#1600000
0!
0L
#1605000
1!
1L
b1000001101010001 P
1O
0N
b1000001101010001 M
16
04
17
13
02
1$
#1610000
0!
0L
#1615000
1!
1L
b10000001101010000 P
0O
1N
b1101010000 M
06
14
07
03
0$
#1620000
0!
0L
#1625000
1!
1L
b1000001101001111 P
1O
0N
b1000001101001111 M
16
04
17
13
12
11
10
0/
1$
#1630000
0!
0L
#1635000
1!
1L
b10000001101001110 P
0O
1N
b1101001110 M
06
14
07
03
0$
#1640000
0!
0L
#1645000
1!
1L
b1000001101001101 P
1O
0N
b1000001101001101 M
16
04
17
13
02
1$
#1650000
0!
0L
#1655000
1!
1L
b10000001101001100 P
0O
1N
b1101001100 M
06
14
07
03
0$
#1660000
0!
0L
#1665000
1!
1L
b1000001101001011 P
1O
0N
b1000001101001011 M
16
04
17
13
12
01
1$
#1670000
0!
0L
#1675000
1!
1L
b10000001101001010 P
0O
1N
b1101001010 M
06
14
07
03
0$
#1680000
0!
0L
#1685000
1!
1L
b1000001101001001 P
1O
0N
b1000001101001001 M
16
04
17
13
02
1$
#1690000
0!
0L
#1695000
1!
1L
b10000001101001000 P
0O
1N
b1101001000 M
06
14
07
03
0$
#1700000
0!
0L
#1705000
1!
1L
b1000001101000111 P
1O
0N
b1000001101000111 M
16
04
17
13
12
11
00
1$
#1710000
0!
0L
#1715000
1!
1L
b10000001101000110 P
0O
1N
b1101000110 M
06
14
07
03
0$
#1720000
0!
0L
#1725000
1!
1L
b1000001101000101 P
1O
0N
b1000001101000101 M
16
04
17
13
02
1$
#1730000
0!
0L
#1735000
1!
1L
b10000001101000100 P
0O
1N
b1101000100 M
06
14
07
03
0$
#1740000
0!
0L
#1745000
1!
1L
b1000001101000011 P
1O
0N
b1000001101000011 M
16
04
17
13
12
01
1$
#1750000
0!
0L
#1755000
1!
1L
b10000001101000010 P
0O
1N
b1101000010 M
06
14
07
03
0$
#1760000
0!
0L
#1765000
1!
1L
b1000001101000001 P
1O
0N
b1000001101000001 M
16
04
17
13
02
1$
#1770000
0!
0L
#1775000
1!
1L
b10000001101000000 P
0O
1N
b1101000000 M
06
14
07
03
0$
#1780000
0!
0L
#1785000
1!
1L
b1000001100111111 P
1O
0N
b1000001100111111 M
16
04
17
13
12
11
10
1/
1.
0-
1$
#1790000
0!
0L
#1795000
1!
1L
b10000001100111110 P
0O
1N
b1100111110 M
06
14
07
03
0$
#1800000
0!
0L
#1805000
1!
1L
b1000001100111101 P
1O
0N
b1000001100111101 M
16
04
17
13
02
1$
#1810000
0!
0L
#1815000
1!
1L
b10000001100111100 P
0O
1N
b1100111100 M
06
14
07
03
0$
#1820000
0!
0L
#1825000
1!
1L
b1000001100111011 P
1O
0N
b1000001100111011 M
16
04
17
13
12
01
1$
#1830000
0!
0L
#1835000
1!
1L
b10000001100111010 P
0O
1N
b1100111010 M
06
14
07
03
0$
#1840000
0!
0L
#1845000
1!
1L
b1000001100111001 P
1O
0N
b1000001100111001 M
16
04
17
13
02
1$
#1850000
0!
0L
#1855000
1!
1L
b10000001100111000 P
0O
1N
b1100111000 M
06
14
07
03
0$
#1860000
0!
0L
#1865000
1!
1L
b1000001100110111 P
1O
0N
b1000001100110111 M
16
04
17
13
12
11
00
1$
#1870000
0!
0L
#1875000
1!
1L
b10000001100110110 P
0O
1N
b1100110110 M
06
14
07
03
0$
#1880000
0!
0L
#1885000
1!
1L
b1000001100110101 P
1O
0N
b1000001100110101 M
16
04
17
13
02
1$
#1890000
0!
0L
#1895000
1!
1L
b10000001100110100 P
0O
1N
b1100110100 M
06
14
07
03
0$
#1900000
0!
0L
#1905000
1!
1L
b1000001100110011 P
1O
0N
b1000001100110011 M
16
04
17
13
12
01
1$
#1910000
0!
0L
#1915000
1!
1L
b10000001100110010 P
0O
1N
b1100110010 M
06
14
07
03
0$
#1920000
0!
0L
