HW3/RAM.v
`timescale 1ns / 1ps

module RAM
  #()
  (
  input W,
  input clk, 
  input [11:0] addr,
  inout [15:0] data
  );
  // initial mem
  reg [15:0] mem [1 << 12 - 1 : 0];
  // data has two modes --> driven by mem / driven by input
  // we assign data if W is 1 else we just give it a high z value 
  // this way we can drive the input value to data wire , if W is 0

  assign data = W ? 16'bz : mem[addr];
  
  // this saved data whenever W is 1
  always @(posedge clk)begin
    if (W) mem[addr] <= data;
    
  end
  
endmodule

module TB() ;
  // regular wire/reg initial
  reg W;
  reg clk;
  wire [15:0] data; 
  reg [11:0] addr; 
  
  // driver to the inout wire
  reg [15:0] driver;
  
  // assign the driver if we need to give it a input
  assign data  = W ? driver : 16'bz;
  
  // use the module vreated
  RAM R01(.W(W), .clk(clk) ,.data(data) ,.addr(addr));

  // initial of the clock 
  always #5 clk = ~clk;
  
  initial begin 
    $dumpfile("vcd.vcd");
    $dumpvars(0, TB);
    
    clk = 0;
    W = 0;
    addr = 0;
    driver = 0;
        
    $monitor("write value : %d\ninput/output value : %d\naddres value : %d" ,W ,data ,addr);  

    #10 
     $display("writing some values");
    W <= 1;
    addr <= 100;
    driver = 200;
    

    #10
    W <= 1;
    addr <= 200;
    driver = 100;
    
    #10
    W <= 1;
    addr <= 300;
    driver = 300;
  
   
    #10 
    $display("read some values");
    W <= 0;
    addr <= 200;
    driver = 0;
    
    #10
    W <= 0;
    addr <= 100;
    
    #10 
    W <= 0;
    addr <= 400;
    
    
 
    #10
    $display("overwrite and write some other values");
    
    W <= 1;
    addr <= 300;
    driver = 400;
    
    #10
    W <= 1;
    addr <= 400;
    driver = 300;
    
    #10
    W <= 1;
    addr <= 500;
    driver = 500;
    
    #10
    $display("read some values");
    W <= 0;
    addr <= 500;
    
    #10
    W <= 0;
    addr <= 300;

    #10
    W <= 0;
    addr <= 400;
    
    #20000
    $finish ;
  end
  
endmodule

HW3/vcd.vcd
$date
	Mon Jun 05 14:41:44 2023
$end
$version
	ModelSim Version 10.1d
$end
$timescale
	1ps
$end
$scope module TB $end
$var reg 1 ! W $end
$var reg 1 " clk $end
$var wire 1 # data [15] $end
$var wire 1 $ data [14] $end
$var wire 1 % data [13] $end
$var wire 1 & data [12] $end
$var wire 1 ' data [11] $end
$var wire 1 ( data [10] $end
$var wire 1 ) data [9] $end
$var wire 1 * data [8] $end
$var wire 1 + data [7] $end
$var wire 1 , data [6] $end
$var wire 1 - data [5] $end
$var wire 1 . data [4] $end
$var wire 1 / data [3] $end
$var wire 1 0 data [2] $end
$var wire 1 1 data [1] $end
$var wire 1 2 data [0] $end
$var reg 12 3 addr [11:0] $end
$var reg 16 4 driver [15:0] $end
$scope module R01 $end
$var wire 1 5 W $end
$var wire 1 6 clk $end
$var wire 1 7 addr [11] $end
$var wire 1 8 addr [10] $end
$var wire 1 9 addr [9] $end
$var wire 1 : addr [8] $end
$var wire 1 ; addr [7] $end
$var wire 1 < addr [6] $end
$var wire 1 = addr [5] $end
$var wire 1 > addr [4] $end
$var wire 1 ? addr [3] $end
$var wire 1 @ addr [2] $end
$var wire 1 A addr [1] $end
$var wire 1 B addr [0] $end
$var wire 1 # data [15] $end
$var wire 1 $ data [14] $end
$var wire 1 % data [13] $end
$var wire 1 & data [12] $end
$var wire 1 ' data [11] $end
$var wire 1 ( data [10] $end
$var wire 1 ) data [9] $end
$var wire 1 * data [8] $end
$var wire 1 + data [7] $end
$var wire 1 , data [6] $end
$var wire 1 - data [5] $end
$var wire 1 . data [4] $end
$var wire 1 / data [3] $end
$var wire 1 0 data [2] $end
$var wire 1 1 data [1] $end
$var wire 1 2 data [0] $end
$upscope $end
$upscope $end
$enddefinitions $end
#0
$dumpvars
0!
0"
b0 3
b0 4
x2
x1
x0
x/
x.
x-
x,
x+
x*
x)
x(
x'
x&
x%
x$
x#
0B
0A
0@
0?
0>
0=
0<
0;
0:
09
08
07
06
05
$end
#5000
1"
16
#10000
b11001000 4
0"
06
1!
b1100100 3
15
1@
1=
1<
02
01
00
1/
0.
0-
1,
1+
0*
0)
0(
0'
0&
0%
0$
0#
#15000
1"
16
#20000
b1100100 4
0"
10
0/
1-
0+
06
b11001000 3
0@
1?
0=
1;
#25000
1"
16
#30000
b100101100 4
0"
1/
0,
1*
06
b100101100 3
1@
1=
0<
0;
1:
#35000
1"
16
#40000
b0 4
0"
00
0/
0-
0*
06
0!
b11001000 3
05
0@
0=
1<
1;
0:
z2
z1
z0
z/
z.
z-
z,
z+
z*
z)
z(
z'
z&
z%
z$
z#
02
01
10
0/
0.
1-
1,
0+
0*
0)
0(
0'
0&
0%
0$
0#
#45000
1"
16
#50000
0"
06
b1100100 3
1@
0?
1=
0;
00
1/
0-
1+
#55000
1"
16
#60000
0"
06
b110010000 3
0@
1>
0=
0<
1;
1:
x2
x1
x0
x/
x.
x-
x,
x+
x*
x)
x(
x'
x&
x%
x$
x#
#65000
1"
16
#70000
b110010000 4
0"
06
1!
b100101100 3
15
1@
1?
0>
1=
0;
02
01
00
0/
1.
0-
0,
1+
1*
0)
0(
0'
0&
0%
0$
0#
#75000
1"
16
#80000
b100101100 4
0"
10
1/
0.
1-
0+
06
b110010000 3
0@
0?
1>
0=
1;
#85000
1"
16
#90000
b111110100 4
0"
0/
1.
1,
1+
06
b111110100 3
1@
1=
1<
#95000
1"
16
#100000
0"
06
0!
z2
z1
z0
z/
z.
z-
z,
z+
z*
z)
z(
z'
z&
z%
z$
z#
05
02
01
10
0/
1.
1-
1,
1+
1*
0)
0(
0'
0&
0%
0$
0#
#105000
1"
16
#110000
0"
06
b100101100 3
1?
0>
0<
0;
00
0-
0,
#115000
1"
16
#120000
0"
06
b110010000 3
0@
0?
1>
0=
1;
10
1/
0.
1-
0+
